{"characters": [
  {"name": "sorcerer", "stats": [[7, 12, 16, 7], [14, 18, 23, 15], [22, 27, 32, 24], [31, 36, 40, 33], [40, 40, 40, 40]]},
  {"name": "cleric", "stats": [[12, 8, 7, 16], [18, 15, 14, 23], [27, 24, 22, 32], [37, 33, 30, 40], [40, 40, 40, 40]]},
  {"name": "thief", "stats": [[9, 13, 10, 8], [16, 21, 18, 15], [24, 31, 27, 23], [33, 40, 36, 31], [40, 40, 40, 40]]},
  {"name": "deprived", "stats": [[10, 10, 10, 10], [20, 20, 20, 20], [30, 30, 30, 30], [40, 40, 40, 40]]},
  {"name": "mercenary", "stats": [[10, 16, 10, 8], [17, 22, 17, 14], [26, 32, 26, 21], [35, 40, 35, 30], [40, 40, 40, 40]]},
  {"name": "pyromancer", "stats": [[12, 9, 14, 14], [17, 13, 21, 19], [26, 20, 31, 28], [35, 27, 40, 38], [40, 40, 40, 40]]}
], "weapons": []}